nicotine_plus-3.3.10.data/data/share/applications/org.nicotine_plus.Nicotine.desktop
nicotine_plus-3.3.10.data/data/share/icons/hicolor/128x128/apps/org.nicotine_plus.Nicotine.png
nicotine_plus-3.3.10.data/data/share/icons/hicolor/128x128@2/apps/org.nicotine_plus.Nicotine.png
nicotine_plus-3.3.10.data/data/share/icons/hicolor/16x16/apps/org.nicotine_plus.Nicotine.png
nicotine_plus-3.3.10.data/data/share/icons/hicolor/16x16@2/apps/org.nicotine_plus.Nicotine.png
nicotine_plus-3.3.10.data/data/share/icons/hicolor/24x24/apps/org.nicotine_plus.Nicotine.png
nicotine_plus-3.3.10.data/data/share/icons/hicolor/24x24@2/apps/org.nicotine_plus.Nicotine.png
nicotine_plus-3.3.10.data/data/share/icons/hicolor/256x256/apps/org.nicotine_plus.Nicotine.png
nicotine_plus-3.3.10.data/data/share/icons/hicolor/256x256@2/apps/org.nicotine_plus.Nicotine.png
nicotine_plus-3.3.10.data/data/share/icons/hicolor/32x32/apps/org.nicotine_plus.Nicotine.png
nicotine_plus-3.3.10.data/data/share/icons/hicolor/32x32@2/apps/org.nicotine_plus.Nicotine.png
nicotine_plus-3.3.10.data/data/share/icons/hicolor/48x48/apps/org.nicotine_plus.Nicotine.png
nicotine_plus-3.3.10.data/data/share/icons/hicolor/48x48@2/apps/org.nicotine_plus.Nicotine.png
nicotine_plus-3.3.10.data/data/share/icons/hicolor/64x64/apps/org.nicotine_plus.Nicotine.png
nicotine_plus-3.3.10.data/data/share/icons/hicolor/64x64@2/apps/org.nicotine_plus.Nicotine.png
nicotine_plus-3.3.10.data/data/share/icons/hicolor/scalable/apps/org.nicotine_plus.Nicotine-away.svg
nicotine_plus-3.3.10.data/data/share/icons/hicolor/scalable/apps/org.nicotine_plus.Nicotine-connect.svg
nicotine_plus-3.3.10.data/data/share/icons/hicolor/scalable/apps/org.nicotine_plus.Nicotine-disconnect.svg
nicotine_plus-3.3.10.data/data/share/icons/hicolor/scalable/apps/org.nicotine_plus.Nicotine-msg.svg
nicotine_plus-3.3.10.data/data/share/icons/hicolor/scalable/apps/org.nicotine_plus.Nicotine.svg
nicotine_plus-3.3.10.dist-info/AUTHORS.md
nicotine_plus-3.3.10.dist-info/COPYING
nicotine_plus-3.3.10.dist-info/METADATA
nicotine_plus-3.3.10.dist-info/WHEEL
nicotine_plus-3.3.10.dist-info/top_level.txt
nicotine_plus-3.3.10.dist-info/RECORD
