Metadata-Version: 2.2
Name: nicotine-plus
Version: 3.3.10
Summary: Graphical client for the Soulseek peer-to-peer network
Home-page: https://nicotine-plus.org
Author: Nicotine+ Team
Author-email: nicotine-team@lists.launchpad.net
License: GPLv3+
Classifier: Development Status :: 5 - Production/Stable
Classifier: Environment :: X11 Applications :: GTK
Classifier: Intended Audience :: End Users/Desktop
Classifier: License :: OSI Approved :: GNU General Public License v3 or later (GPLv3+)
Classifier: Operating System :: OS Independent
Classifier: Programming Language :: Python
Classifier: Topic :: Communications :: Chat
Classifier: Topic :: Communications :: File Sharing
Classifier: Topic :: Internet
Classifier: Topic :: System :: Networking
Requires-Python: >=3.6
License-File: COPYING
License-File: AUTHORS.md
Requires-Dist: PyGObject>=3.22
Provides-Extra: packaging
Requires-Dist: cx_Freeze; extra == "packaging"
Provides-Extra: tests
Requires-Dist: pycodestyle; extra == "tests"
Requires-Dist: pylint; extra == "tests"
